{
  "automated": [
    {
      "name": "lint",
      "result": "pass",
      "detail": "py_compile pass on all 4 changed source files"
    },
    {
      "name": "types",
      "result": "skipped"
    },
    {
      "name": "tests",
      "result": "pass",
      "detail": "168 passed in 2.13s"
    }
  ],
  "blockers": [],
  "branch": "feature/context-graph",
  "feature": "context-graph",
  "invariants": {
    "findings": [],
    "summary": {
      "fail": 0,
      "total": 0,
      "warn": 0
    }
  },
  "packages": [
    {
      "checks": [
        {
          "cmd": "python3 -m py_compile scripts/context/phases/impact.py scripts/context/__init__.py scripts/context/storage.py scripts/workflow_memory.py",
          "name": "lint",
          "result": "pass"
        },
        {
          "cmd": null,
          "name": "typecheck",
          "result": "skipped"
        },
        {
          "cmd": "python3 -m pytest tests/test_context_*.py -x",
          "name": "test",
          "result": "pass",
          "detail": "168 passed"
        }
      ],
      "kind": "python",
      "name": "cnogo-scripts",
      "path": "scripts"
    }
  ],
  "patternCompliance": [
    {
      "pattern": "stdlib-only",
      "status": "pass",
      "detail": "All new code uses only stdlib imports (collections, dataclasses, argparse, sqlite3)"
    },
    {
      "pattern": "existing-cli-pattern",
      "status": "pass",
      "detail": "graph-* commands follow same argparse + dispatch pattern as existing commands"
    },
    {
      "pattern": "TDD",
      "status": "pass",
      "detail": "All 3 tasks followed RED-GREEN cycle; 34 new tests (13+9+12)"
    }
  ],
  "performanceFindings": [
    {
      "severity": "info",
      "detail": "BFS impact_analysis uses visited set for cycle detection; SQL queries use indexed columns (file_path, source, target, type)",
      "location": "scripts/context/phases/impact.py"
    }
  ],
  "principleNotes": [
    {
      "principle": "Simplicity First",
      "status": "pass",
      "detail": "BFS implementation is ~60 LOC; CLI handlers are thin wrappers delegating to ContextGraph methods"
    },
    {
      "principle": "Surgical Changes",
      "status": "pass",
      "detail": "Only files in plan scope were modified; no drive-by refactors"
    },
    {
      "principle": "Goal-Driven Execution",
      "status": "pass",
      "detail": "All 3 plan tasks verified with fresh test evidence"
    }
  ],
  "schemaVersion": 4,
  "securityFindings": [],
  "stageReviews": [
    {
      "stage": "spec-compliance",
      "status": "pass",
      "findings": [],
      "evidence": [
        "Plan goal: 'Implement impact analysis (BFS blast radius) and expose the context graph via CLI commands' — all 3 tasks delivered",
        "Task 1: impact.py created with ImpactResult + impact_analysis(), wired into ContextGraph.impact() — 13 tests pass",
        "Task 2: get_related_nodes() added, context() implemented with full neighborhood — 9 tests pass",
        "Task 3: 4 CLI subcommands (graph-index/query/impact/context) with --repo flag, bypassing memory DB check — 12 tests pass",
        "planVerify: 168 tests pass + graph-index --help works",
        "Changed files match plan scope exactly (plus test_context_graph.py for stale stub updates)"
      ],
      "notes": "All 3 tasks complete. Plan scope respected. Only pre-existing warnings from earlier plans."
    },
    {
      "stage": "code-quality",
      "status": "pass",
      "findings": [
        {
          "severity": "info",
          "location": "scripts/workflow_memory.py:cmd_graph_index",
          "detail": "Accesses storage._conn directly for rel/file counts. Minor — stats could be added to GraphStorage API later."
        },
        {
          "severity": "info",
          "location": "tests/test_context_cli.py:test_context_known_node",
          "detail": "Accepts returncode 0 or 1 — soft assertion. Acceptable for integration test where node ID format may vary."
        }
      ],
      "evidence": [
        "py_compile: all 4 source files pass",
        "168/168 tests pass",
        "No security findings (no user input beyond CLI args, parameterized SQL throughout)",
        "BFS uses visited set preventing infinite loops",
        "CLI commands properly close() graph in finally blocks",
        "graph commands correctly exempt from memory engine DB check"
      ],
      "notes": "Clean implementation. Two info-level observations, no blockers."
    }
  ],
  "scoring": {
    "correctness": 2,
    "security": 2,
    "contractCompliance": 2,
    "testCoverage": 2,
    "codeClarity": 2,
    "performance": 2,
    "operationalReadiness": 1,
    "total": 13,
    "maxScore": 14,
    "notes": "Operational readiness at 1/2: CLI works but no --json output flag on graph commands for machine consumption. Non-blocking."
  },
  "timestamp": "2026-02-28T02:15:00Z",
  "tokenTelemetry": {
    "checksRun": 2,
    "checksSkipped": 1,
    "inputTokens": 0,
    "outputTokens": 0,
    "savedTokens": 0,
    "savingsPct": 0.0
  },
  "verdict": "pass",
  "warnings": []
}
